{
  "id": "Lux",
  "name_ja": "ラックス",
  "data": [
    {
      "updatetime": "2025/08/28",
      "lane": "MID",
      "rank": "Emerald",
      "winrate": 50.8641,
      "pickrate": 8.3466,
      "banrate": 27.5374
    },
    {
      "updatetime": "2025/08/28",
      "lane": "SUP",
      "rank": "Emerald",
      "winrate": 51.1701,
      "pickrate": 15.931400000000002,
      "banrate": 27.5374
    },
    {
      "updatetime": "2025/08/28",
      "lane": "MID",
      "rank": "Diamond",
      "winrate": 50.9184,
      "pickrate": 7.871300000000001,
      "banrate": 32.8455
    },
    {
      "updatetime": "2025/08/28",
      "lane": "SUP",
      "rank": "Diamond",
      "winrate": 50.4235,
      "pickrate": 12.1043,
      "banrate": 32.8455
    },
    {
      "updatetime": "2025/08/28",
      "lane": "MID",
      "rank": "Master",
      "winrate": 50.6181,
      "pickrate": 7.9368,
      "banrate": 32.0986
    },
    {
      "updatetime": "2025/08/28",
      "lane": "SUP",
      "rank": "Master",
      "winrate": 50.2167,
      "pickrate": 11.5231,
      "banrate": 32.0986
    },
    {
      "updatetime": "2025/08/28",
      "lane": "MID",
      "rank": "Challenger",
      "winrate": 47.8804,
      "pickrate": 5.4421,
      "banrate": 5.6444
    },
    {
      "updatetime": "2025/08/28",
      "lane": "SUP",
      "rank": "Challenger",
      "winrate": 47.543600000000005,
      "pickrate": 6.8833,
      "banrate": 5.6444
    },
    {
      "updatetime": "2025/08/28",
      "lane": "MID",
      "rank": "Legendary_rank",
      "winrate": 48.2234,
      "pickrate": 5.4036,
      "banrate": 9.9537
    },
    {
      "updatetime": "2025/08/28",
      "lane": "SUP",
      "rank": "Legendary_rank",
      "winrate": 47.4876,
      "pickrate": 8.124,
      "banrate": 9.9537
    },
    {
      "updatetime": "2025/09/01",
      "lane": "MID",
      "rank": "Emerald",
      "winrate": 51.8647,
      "pickrate": 8.0324,
      "banrate": 27.4043
    },
    {
      "updatetime": "2025/09/01",
      "lane": "SUP",
      "rank": "Emerald",
      "winrate": 51.2339,
      "pickrate": 16.2828,
      "banrate": 27.4043
    },
    {
      "updatetime": "2025/09/01",
      "lane": "MID",
      "rank": "Diamond",
      "winrate": 50.8198,
      "pickrate": 7.6653,
      "banrate": 33.454
    },
    {
      "updatetime": "2025/09/01",
      "lane": "SUP",
      "rank": "Diamond",
      "winrate": 50.2613,
      "pickrate": 12.1889,
      "banrate": 33.454
    },
    {
      "updatetime": "2025/09/01",
      "lane": "MID",
      "rank": "Master",
      "winrate": 50.5066,
      "pickrate": 7.674200000000001,
      "banrate": 32.868199999999995
    },
    {
      "updatetime": "2025/09/01",
      "lane": "SUP",
      "rank": "Master",
      "winrate": 50.030300000000004,
      "pickrate": 11.6284,
      "banrate": 32.868199999999995
    },
    {
      "updatetime": "2025/09/01",
      "lane": "MID",
      "rank": "Challenger",
      "winrate": 47.4373,
      "pickrate": 5.5487,
      "banrate": 7.4768
    },
    {
      "updatetime": "2025/09/01",
      "lane": "SUP",
      "rank": "Challenger",
      "winrate": 48.6984,
      "pickrate": 7.411700000000001,
      "banrate": 7.4768
    },
    {
      "updatetime": "2025/09/01",
      "lane": "MID",
      "rank": "Legendary_rank",
      "winrate": 48.1458,
      "pickrate": 4.9493,
      "banrate": 10.618500000000001
    },
    {
      "updatetime": "2025/09/01",
      "lane": "SUP",
      "rank": "Legendary_rank",
      "winrate": 49.2052,
      "pickrate": 8.387799999999999,
      "banrate": 10.618500000000001
    },
    {
      "updatetime": "2025/09/02",
      "lane": "MID",
      "rank": "Emerald",
      "winrate": 51.153099999999995,
      "pickrate": 8.042100000000001,
      "banrate": 27.652700000000003
    },
    {
      "updatetime": "2025/09/02",
      "lane": "SUP",
      "rank": "Emerald",
      "winrate": 51.330799999999996,
      "pickrate": 16.0906,
      "banrate": 27.652700000000003
    },
    {
      "updatetime": "2025/09/02",
      "lane": "MID",
      "rank": "Diamond",
      "winrate": 50.980199999999996,
      "pickrate": 7.6474,
      "banrate": 33.582
    },
    {
      "updatetime": "2025/09/02",
      "lane": "SUP",
      "rank": "Diamond",
      "winrate": 50.2028,
      "pickrate": 12.180399999999999,
      "banrate": 33.582
    },
    {
      "updatetime": "2025/09/02",
      "lane": "MID",
      "rank": "Master",
      "winrate": 50.7939,
      "pickrate": 7.657500000000001,
      "banrate": 32.9938
    },
    {
      "updatetime": "2025/09/02",
      "lane": "SUP",
      "rank": "Master",
      "winrate": 50.110600000000005,
      "pickrate": 11.667900000000001,
      "banrate": 32.9938
    },
    {
      "updatetime": "2025/09/02",
      "lane": "MID",
      "rank": "Challenger",
      "winrate": 49.0843,
      "pickrate": 5.5091,
      "banrate": 7.729800000000001
    },
    {
      "updatetime": "2025/09/02",
      "lane": "SUP",
      "rank": "Challenger",
      "winrate": 47.137,
      "pickrate": 7.4166,
      "banrate": 7.729800000000001
    },
    {
      "updatetime": "2025/09/02",
      "lane": "MID",
      "rank": "Legendary_rank",
      "winrate": 48.5193,
      "pickrate": 5.1465,
      "banrate": 10.6301
    },
    {
      "updatetime": "2025/09/02",
      "lane": "SUP",
      "rank": "Legendary_rank",
      "winrate": 47.5572,
      "pickrate": 7.940600000000001,
      "banrate": 10.6301
    },
    {
      "updatetime": "2025/09/09",
      "lane": "MID",
      "rank": "Emerald",
      "winrate": 51.722199999999994,
      "pickrate": 8.3448,
      "banrate": 27.0678
    },
    {
      "updatetime": "2025/09/09",
      "lane": "SUP",
      "rank": "Emerald",
      "winrate": 50.5932,
      "pickrate": 16.486,
      "banrate": 27.0678
    },
    {
      "updatetime": "2025/09/09",
      "lane": "MID",
      "rank": "Diamond",
      "winrate": 51.121700000000004,
      "pickrate": 7.8042,
      "banrate": 33.9329
    },
    {
      "updatetime": "2025/09/09",
      "lane": "SUP",
      "rank": "Diamond",
      "winrate": 49.9841,
      "pickrate": 12.1491,
      "banrate": 33.9329
    },
    {
      "updatetime": "2025/09/09",
      "lane": "MID",
      "rank": "Master",
      "winrate": 50.867799999999995,
      "pickrate": 7.886799999999999,
      "banrate": 33.4205
    },
    {
      "updatetime": "2025/09/09",
      "lane": "SUP",
      "rank": "Master",
      "winrate": 49.791000000000004,
      "pickrate": 11.662799999999999,
      "banrate": 33.4205
    },
    {
      "updatetime": "2025/09/09",
      "lane": "MID",
      "rank": "Challenger",
      "winrate": 49.050700000000006,
      "pickrate": 6.2033,
      "banrate": 10.363999999999999
    },
    {
      "updatetime": "2025/09/09",
      "lane": "SUP",
      "rank": "Challenger",
      "winrate": 48.0347,
      "pickrate": 7.9404,
      "banrate": 10.363999999999999
    },
    {
      "updatetime": "2025/09/09",
      "lane": "MID",
      "rank": "Legendary_rank",
      "winrate": 46.8227,
      "pickrate": 5.0156,
      "banrate": 11.9649
    },
    {
      "updatetime": "2025/09/09",
      "lane": "SUP",
      "rank": "Legendary_rank",
      "winrate": 48.2908,
      "pickrate": 8.0747,
      "banrate": 11.9649
    },
    {
      "updatetime": "2025/09/16",
      "lane": "MID",
      "rank": "Emerald",
      "winrate": 53.2459,
      "pickrate": 7.8458,
      "banrate": 25.194499999999998
    },
    {
      "updatetime": "2025/09/16",
      "lane": "SUP",
      "rank": "Emerald",
      "winrate": 51.0871,
      "pickrate": 16.180600000000002,
      "banrate": 25.194499999999998
    },
    {
      "updatetime": "2025/09/16",
      "lane": "MID",
      "rank": "Diamond",
      "winrate": 51.3505,
      "pickrate": 7.428800000000001,
      "banrate": 32.183499999999995
    },
    {
      "updatetime": "2025/09/16",
      "lane": "SUP",
      "rank": "Diamond",
      "winrate": 49.9507,
      "pickrate": 12.166599999999999,
      "banrate": 32.183499999999995
    },
    {
      "updatetime": "2025/09/16",
      "lane": "MID",
      "rank": "Master",
      "winrate": 51.159600000000005,
      "pickrate": 7.5295000000000005,
      "banrate": 31.7606
    },
    {
      "updatetime": "2025/09/16",
      "lane": "SUP",
      "rank": "Master",
      "winrate": 49.857,
      "pickrate": 11.7814,
      "banrate": 31.7606
    },
    {
      "updatetime": "2025/09/16",
      "lane": "MID",
      "rank": "Challenger",
      "winrate": 49.828,
      "pickrate": 6.477399999999999,
      "banrate": 11.2816
    },
    {
      "updatetime": "2025/09/16",
      "lane": "SUP",
      "rank": "Challenger",
      "winrate": 49.206,
      "pickrate": 8.5037,
      "banrate": 11.2816
    },
    {
      "updatetime": "2025/09/16",
      "lane": "MID",
      "rank": "Legendary_rank",
      "winrate": 50.059,
      "pickrate": 5.2362,
      "banrate": 11.5588
    },
    {
      "updatetime": "2025/09/16",
      "lane": "SUP",
      "rank": "Legendary_rank",
      "winrate": 48.375800000000005,
      "pickrate": 8.4214,
      "banrate": 11.5588
    },
    {
      "updatetime": "2025/09/23",
      "lane": "MID",
      "rank": "Emerald",
      "winrate": 51.8014,
      "pickrate": 7.558199999999999,
      "banrate": 25.6929
    },
    {
      "updatetime": "2025/09/23",
      "lane": "SUP",
      "rank": "Emerald",
      "winrate": 51.512899999999995,
      "pickrate": 15.4493,
      "banrate": 25.6929
    },
    {
      "updatetime": "2025/09/23",
      "lane": "MID",
      "rank": "Diamond",
      "winrate": 50.865899999999996,
      "pickrate": 7.2837,
      "banrate": 32.719
    },
    {
      "updatetime": "2025/09/23",
      "lane": "SUP",
      "rank": "Diamond",
      "winrate": 49.8979,
      "pickrate": 12.0543,
      "banrate": 32.719
    },
    {
      "updatetime": "2025/09/23",
      "lane": "MID",
      "rank": "Master",
      "winrate": 50.7801,
      "pickrate": 7.3753,
      "banrate": 32.3686
    },
    {
      "updatetime": "2025/09/23",
      "lane": "SUP",
      "rank": "Master",
      "winrate": 49.6135,
      "pickrate": 11.723600000000001,
      "banrate": 32.3686
    },
    {
      "updatetime": "2025/09/23",
      "lane": "MID",
      "rank": "Challenger",
      "winrate": 49.2165,
      "pickrate": 6.4177,
      "banrate": 13.5903
    },
    {
      "updatetime": "2025/09/23",
      "lane": "SUP",
      "rank": "Challenger",
      "winrate": 48.2302,
      "pickrate": 8.9054,
      "banrate": 13.5903
    },
    {
      "updatetime": "2025/09/23",
      "lane": "MID",
      "rank": "Legendary_rank",
      "winrate": 49.8461,
      "pickrate": 4.7991,
      "banrate": 12.1736
    },
    {
      "updatetime": "2025/09/23",
      "lane": "SUP",
      "rank": "Legendary_rank",
      "winrate": 48.4728,
      "pickrate": 8.5137,
      "banrate": 12.1736
    },
    {
      "updatetime": "2025/09/30",
      "lane": "MID",
      "rank": "Emerald",
      "winrate": 51.1622,
      "pickrate": 7.3557,
      "banrate": 25.3334
    },
    {
      "updatetime": "2025/09/30",
      "lane": "SUP",
      "rank": "Emerald",
      "winrate": 50.422599999999996,
      "pickrate": 15.721499999999999,
      "banrate": 25.3334
    },
    {
      "updatetime": "2025/09/30",
      "lane": "MID",
      "rank": "Diamond",
      "winrate": 50.818,
      "pickrate": 6.9171,
      "banrate": 32.7496
    },
    {
      "updatetime": "2025/09/30",
      "lane": "SUP",
      "rank": "Diamond",
      "winrate": 50.365,
      "pickrate": 12.195400000000001,
      "banrate": 32.7496
    },
    {
      "updatetime": "2025/09/30",
      "lane": "MID",
      "rank": "Master",
      "winrate": 50.6816,
      "pickrate": 6.993,
      "banrate": 32.5134
    },
    {
      "updatetime": "2025/09/30",
      "lane": "SUP",
      "rank": "Master",
      "winrate": 50.288900000000005,
      "pickrate": 11.8998,
      "banrate": 32.5134
    },
    {
      "updatetime": "2025/09/30",
      "lane": "MID",
      "rank": "Challenger",
      "winrate": 49.9092,
      "pickrate": 6.4873,
      "banrate": 15.2393
    },
    {
      "updatetime": "2025/09/30",
      "lane": "SUP",
      "rank": "Challenger",
      "winrate": 48.9288,
      "pickrate": 9.4282,
      "banrate": 15.2393
    },
    {
      "updatetime": "2025/09/30",
      "lane": "MID",
      "rank": "Legendary_rank",
      "winrate": 49.3444,
      "pickrate": 4.861,
      "banrate": 12.105599999999999
    },
    {
      "updatetime": "2025/09/30",
      "lane": "SUP",
      "rank": "Legendary_rank",
      "winrate": 48.064099999999996,
      "pickrate": 8.5781,
      "banrate": 12.105599999999999
    },
    {
      "updatetime": "2025/10/07",
      "lane": "MID",
      "rank": "Emerald",
      "winrate": 51.76,
      "pickrate": 7.6046000000000005,
      "banrate": 25.050099999999997
    },
    {
      "updatetime": "2025/10/07",
      "lane": "SUP",
      "rank": "Emerald",
      "winrate": 51.3559,
      "pickrate": 16.220499999999998,
      "banrate": 25.050099999999997
    },
    {
      "updatetime": "2025/10/07",
      "lane": "MID",
      "rank": "Diamond",
      "winrate": 50.8451,
      "pickrate": 7.106,
      "banrate": 32.8597
    },
    {
      "updatetime": "2025/10/07",
      "lane": "SUP",
      "rank": "Diamond",
      "winrate": 49.992399999999996,
      "pickrate": 12.3005,
      "banrate": 32.8597
    },
    {
      "updatetime": "2025/10/07",
      "lane": "MID",
      "rank": "Master",
      "winrate": 50.80519999999999,
      "pickrate": 7.1978,
      "banrate": 32.5437
    },
    {
      "updatetime": "2025/10/07",
      "lane": "SUP",
      "rank": "Master",
      "winrate": 49.9647,
      "pickrate": 12.0398,
      "banrate": 32.5437
    },
    {
      "updatetime": "2025/10/07",
      "lane": "MID",
      "rank": "Challenger",
      "winrate": 50.1864,
      "pickrate": 6.8886,
      "banrate": 16.204
    },
    {
      "updatetime": "2025/10/07",
      "lane": "SUP",
      "rank": "Challenger",
      "winrate": 48.804700000000004,
      "pickrate": 9.667,
      "banrate": 16.204
    },
    {
      "updatetime": "2025/10/07",
      "lane": "MID",
      "rank": "Legendary_rank",
      "winrate": 48.419200000000004,
      "pickrate": 4.5172,
      "banrate": 13.207099999999999
    },
    {
      "updatetime": "2025/10/07",
      "lane": "SUP",
      "rank": "Legendary_rank",
      "winrate": 48.4407,
      "pickrate": 8.2133,
      "banrate": 13.207099999999999
    }
  ]
}