[
  {
    "ranking": "1",
    "champion": "ノラ",
    "reason": "SUPのMasterランクでwin↓ pick↑ ban↓。他ランク帯では、Challenger帯でwin↓ pick↑ ban↓、Legendary_rank帯でwin↓ pick↑ ban↓と、全体的に下降トレンドが見られます。"
  },
  {
    "ranking": "2",
    "champion": "ノラ",
    "reason": "MIDのMasterランクでwin↑ pick↑ ban↓。他ランク帯では、Challenger帯でwin↓ pick↑ ban↓、Legendary_rank帯でwin↓ pick↑ ban↓と、全体的に下降トレンドが見られます。"
  },
  {
    "ranking": "3",
    "champion": "ガレン",
    "reason": "TOPのMasterランクでwin↓ pick↓ ban↓。他ランク帯では、Challenger帯でwin↓ pick↓ ban↓、Diamond帯でwin↓ pick↓ ban↓と、全体的に下降トレンドが見られます。"
  },
  {
    "ranking": "4",
    "champion": "スモルダー",
    "reason": "ADCのMasterランクでwin↓ pick↓ ban↓。他ランク帯では、Challenger帯でwin↓ pick↓ ban↓、Diamond帯でwin↓ pick↓ ban↓と、全体的に下降トレンドが見られます。"
  },
  {
    "ranking": "5",
    "champion": "ライズ",
    "reason": "MIDのMasterランクでwin↓ pick↓ ban↓。他ランク帯では、Challenger帯でwin↓ pick↓ ban↓、Diamond帯でwin↓ pick↓ ban↓と、全体的に下降トレンドが見られます。"
  },
  {
    "ranking": "6",
    "champion": "ライズ",
    "reason": "TOPのMasterランクでwin↓ pick↓ ban↓。他ランク帯では、Challenger帯でwin↓ pick↓ ban↓、Diamond帯でwin↓ pick↓ ban↓と、全体的に下降トレンドが見られます。"
  },
  {
    "ranking": "7",
    "champion": "ライズ",
    "reason": "MIDのChallengerランクでwin↓ pick↓ ban↓。他ランク帯では、Master帯でwin↓ pick↓ ban↓、Diamond帯でwin↓ pick↓ ban↓と、全体的に下降トレンドが見られます。"
  },
  {
    "ranking": "8",
    "champion": "ライズ",
    "reason": "TOPのChallengerランクでwin↓ pick↓ ban↓。他ランク帯では、Master帯でwin↓ pick↓ ban↓、Diamond帯でwin↓ pick↓ ban↓と、全体的に下降トレンドが見られます。"
  },
  {
    "ranking": "9",
    "champion": "ライズ",
    "reason": "MIDのDiamondランクでwin↓ pick↓ ban↓。他ランク帯では、Master帯でwin↓ pick↓ ban↓、Challenger帯でwin↓ pick↓ ban↓と、全体的に下降トレンドが見られます。"
  },
  {
    "ranking": "10",
    "champion": "ライズ",
    "reason": "TOPのDiamondランクでwin↓ pick↓ ban↓。他ランク帯では、Master帯でwin↓ pick↓ ban↓、Challenger帯でwin↓ pick↓ ban↓と、全体的に下降トレンドが見られます。"
  },
  {
    "ranking": "11",
    "champion": "ライズ",
    "reason": "MIDのLegendary_rankランクでwin↓ pick↓ ban↓。他ランク帯では、Master帯でwin↓ pick↓ ban↓、Challenger帯でwin↓ pick↓ ban↓と、全体的に下降トレンドが見られます。"
  },
  {
    "ranking": "12",
    "champion": "ライズ",
    "reason": "TOPのLegendary_rankランクでwin↑ pick↓ ban↓。他ランク帯では、Master帯でwin↓ pick↓ ban↓、Challenger帯でwin↓ pick↓ ban↓と、全体的に下降トレンドが見られます。"
  },
  {
    "ranking": "13",
    "champion": "ダイアナ",
    "reason": "MIDのChallengerランクでwin↓ pick↑ ban↑。他ランク帯では、JGのChallenger帯でwin↓ pick↑ ban↓と、全体的に下降トレンドが見られます。"
  },
  {
    "ranking": "14",
    "champion": "ノラ",
    "reason": "SUPのMasterランクでwin↓ pick↑ ban↓。他ランク帯では、Challenger帯でwin↓ pick↑ ban↓、Legendary_rank帯でwin↓ pick↑ ban↓と、全体的に下降トレンドが見られます。"
  },
  {
    "ranking": "15",
    "champion": "ノラ",
    "reason": "MIDのChallengerランクでwin↓ pick↑ ban↓。他ランク帯では、Master帯でwin↓ pick↑ ban↓、Legendary_rank帯でwin↓ pick↑ ban↓と、全体的に下降トレンドが見られます。"
  }
]