{
  "id": "Taliyah",
  "name_ja": "タリヤ",
  "data": [],
  "patches": [
    {
      "patch_name": "ワイルドリフト パッチノート 7.1f",
      "updatetime": "2026/06/10",
      "data": [
        {
          "lane": "MID",
          "rank": "Emerald",
          "winrate": 52.7089,
          "pickrate": 5.7153,
          "banrate": 9.4748
        },
        {
          "lane": "JG",
          "rank": "Emerald",
          "winrate": 53.4175,
          "pickrate": 2.3547,
          "banrate": 9.4748
        },
        {
          "lane": "MID",
          "rank": "Diamond",
          "winrate": 52.0572,
          "pickrate": 4.987699999999999,
          "banrate": 43.7697
        },
        {
          "lane": "JG",
          "rank": "Diamond",
          "winrate": 52.2489,
          "pickrate": 2.0943,
          "banrate": 43.7697
        },
        {
          "lane": "MID",
          "rank": "Master",
          "winrate": 52.2289,
          "pickrate": 4.7575,
          "banrate": 48.1968
        },
        {
          "lane": "JG",
          "rank": "Master",
          "winrate": 52.4204,
          "pickrate": 2.0762,
          "banrate": 48.1968
        },
        {
          "lane": "MID",
          "rank": "Challenger",
          "winrate": 51.325900000000004,
          "pickrate": 4.5755,
          "banrate": 62.5839
        },
        {
          "lane": "JG",
          "rank": "Challenger",
          "winrate": 51.582499999999996,
          "pickrate": 2.2828,
          "banrate": 62.5839
        },
        {
          "lane": "MID",
          "rank": "Legendary_rank",
          "winrate": 54.5252,
          "pickrate": 4.0231,
          "banrate": 70.8534
        },
        {
          "lane": "JG",
          "rank": "Legendary_rank",
          "winrate": 53.5395,
          "pickrate": 1.8339999999999999,
          "banrate": 70.8534
        }
      ]
    },
    {
      "patch_name": "ワイルドリフト パッチノート 7.1g",
      "updatetime": "2026/06/23",
      "data": [
        {
          "lane": "MID",
          "rank": "Emerald",
          "winrate": 54.3385,
          "pickrate": 3.9875000000000003,
          "banrate": 5.3829
        },
        {
          "lane": "JG",
          "rank": "Emerald",
          "winrate": 52.88890000000001,
          "pickrate": 2.1271,
          "banrate": 5.3829
        },
        {
          "lane": "MID",
          "rank": "Diamond",
          "winrate": 53.244499999999995,
          "pickrate": 4.2901,
          "banrate": 34.4204
        },
        {
          "lane": "JG",
          "rank": "Diamond",
          "winrate": 53.7884,
          "pickrate": 1.8613000000000002,
          "banrate": 34.4204
        },
        {
          "lane": "MID",
          "rank": "Master",
          "winrate": 53.2397,
          "pickrate": 4.2388,
          "banrate": 38.0993
        },
        {
          "lane": "JG",
          "rank": "Master",
          "winrate": 53.6779,
          "pickrate": 1.8515,
          "banrate": 38.0993
        },
        {
          "lane": "MID",
          "rank": "Challenger",
          "winrate": 53.339000000000006,
          "pickrate": 4.2407,
          "banrate": 51.075199999999995
        },
        {
          "lane": "JG",
          "rank": "Challenger",
          "winrate": 54.240500000000004,
          "pickrate": 2.1042,
          "banrate": 51.075199999999995
        },
        {
          "lane": "MID",
          "rank": "Legendary_rank",
          "winrate": 52.4146,
          "pickrate": 4.1337,
          "banrate": 60.770199999999996
        },
        {
          "lane": "JG",
          "rank": "Legendary_rank",
          "winrate": 55.4756,
          "pickrate": 1.921,
          "banrate": 60.770199999999996
        }
      ]
    },
    {
      "patch_name": "ワイルドリフト パッチノート 7.1h",
      "updatetime": "2026/07/07",
      "data": [
        {
          "lane": "MID",
          "rank": "Emerald",
          "winrate": 50.85229999999999,
          "pickrate": 3.1875,
          "banrate": 3.1037
        },
        {
          "lane": "JG",
          "rank": "Emerald",
          "winrate": 50.0,
          "pickrate": 1.5847,
          "banrate": 3.1037
        },
        {
          "lane": "MID",
          "rank": "Diamond",
          "winrate": 51.2235,
          "pickrate": 3.4438999999999997,
          "banrate": 25.652199999999997
        },
        {
          "lane": "JG",
          "rank": "Diamond",
          "winrate": 50.635799999999996,
          "pickrate": 1.4711999999999998,
          "banrate": 25.652199999999997
        },
        {
          "lane": "MID",
          "rank": "Master",
          "winrate": 51.3546,
          "pickrate": 3.4457,
          "banrate": 28.290599999999998
        },
        {
          "lane": "JG",
          "rank": "Master",
          "winrate": 50.851400000000005,
          "pickrate": 1.4933,
          "banrate": 28.290599999999998
        },
        {
          "lane": "MID",
          "rank": "Challenger",
          "winrate": 52.148399999999995,
          "pickrate": 3.6748999999999996,
          "banrate": 38.7892
        },
        {
          "lane": "JG",
          "rank": "Challenger",
          "winrate": 50.832100000000004,
          "pickrate": 1.6744999999999999,
          "banrate": 38.7892
        },
        {
          "lane": "MID",
          "rank": "Legendary_rank",
          "winrate": 51.340399999999995,
          "pickrate": 3.8533999999999997,
          "banrate": 47.0617
        },
        {
          "lane": "JG",
          "rank": "Legendary_rank",
          "winrate": 50.2315,
          "pickrate": 1.6840000000000002,
          "banrate": 47.0617
        }
      ]
    },
    {
      "patch_name": "ワイルドリフト パッチノート 7.2",
      "updatetime": "2026/07/14",
      "data": [
        {
          "lane": "MID",
          "rank": "Emerald",
          "winrate": 49.7667,
          "pickrate": 3.0422000000000002,
          "banrate": 4.2896
        },
        {
          "lane": "JG",
          "rank": "Emerald",
          "winrate": 48.993700000000004,
          "pickrate": 1.2541,
          "banrate": 4.2896
        },
        {
          "lane": "MID",
          "rank": "Diamond",
          "winrate": 50.929,
          "pickrate": 3.718,
          "banrate": 10.7715
        },
        {
          "lane": "JG",
          "rank": "Diamond",
          "winrate": 48.427,
          "pickrate": 1.5063,
          "banrate": 10.7715
        },
        {
          "lane": "MID",
          "rank": "Master",
          "winrate": 51.5734,
          "pickrate": 4.3236,
          "banrate": 14.510600000000002
        },
        {
          "lane": "JG",
          "rank": "Master",
          "winrate": 48.870599999999996,
          "pickrate": 1.6732,
          "banrate": 14.510600000000002
        }
      ]
    },
    {
      "patch_name": "ワイルドリフト パッチノート 7.2a",
      "updatetime": "2026/07/21",
      "data": [
        {
          "lane": "MID",
          "rank": "Emerald",
          "winrate": 47.814800000000005,
          "pickrate": 2.5978000000000003,
          "banrate": 2.6315999999999997
        },
        {
          "lane": "JG",
          "rank": "Emerald",
          "winrate": 50.1272,
          "pickrate": 1.0624,
          "banrate": 2.6315999999999997
        },
        {
          "lane": "MID",
          "rank": "Diamond",
          "winrate": 51.574799999999996,
          "pickrate": 3.1269,
          "banrate": 7.063
        },
        {
          "lane": "JG",
          "rank": "Diamond",
          "winrate": 49.6678,
          "pickrate": 1.1608,
          "banrate": 7.063
        },
        {
          "lane": "MID",
          "rank": "Master",
          "winrate": 52.0616,
          "pickrate": 3.3734,
          "banrate": 8.699900000000001
        },
        {
          "lane": "JG",
          "rank": "Master",
          "winrate": 49.5809,
          "pickrate": 1.2243,
          "banrate": 8.699900000000001
        },
        {
          "lane": "MID",
          "rank": "Challenger",
          "winrate": 56.7568,
          "pickrate": 5.7948,
          "banrate": 7.0478
        },
        {
          "lane": "JG",
          "rank": "Challenger",
          "winrate": 35.7143,
          "pickrate": 1.0963,
          "banrate": 7.0478
        }
      ]
    }
  ]
}